{
    "appId": 435150,
    "hasAchievements": true,
    "total": 97,
    "unlocked": 14,
    "gameName": "Divinity: Original Sin 2",
    "achievements": [
        {
            "apiName": "DOS2_Quest1",
            "unlocked": true,
            "unlockedAt": "2018-11-20T12:30:09.000Z",
            "displayName": "Thunders of the Upper Deep",
            "description": "Escape the kraken's clutches",
            "iconUrl": "0f2e4282150bd16233fc9611adccb1cd51506a1c.jpg",
            "iconGrayUrl": "dc70ad59dccc49ca1f00313a79e350cb0d7c8743.jpg",
            "hidden": false,
            "globalPct": 80.6
        },
        {
            "apiName": "DOS2_Quest2",
            "unlocked": true,
            "unlockedAt": "2018-11-20T12:30:09.000Z",
            "displayName": "Reaper's Eye",
            "description": "Arrive at Reaper's Eye",
            "iconUrl": "16c4753abb06c9477ee9d6cf75e2e84ecd677d80.jpg",
            "iconGrayUrl": "febd32306a60c94d14bf115f9c4d0f32e6db53b7.jpg",
            "hidden": false,
            "globalPct": 82.3
        },
        {
            "apiName": "DOS2_Quest3",
            "unlocked": true,
            "unlockedAt": "2018-11-23T19:10:04.000Z",
            "displayName": "Gladiator",
            "description": "Become champion of the Fort Joy arena",
            "iconUrl": "eda08b79a3a4dc41918ec446afeab5d130c28cb2.jpg",
            "iconGrayUrl": "d19bc5323d0e4c093498b26b73366a5e0bb494a2.jpg",
            "hidden": false,
            "globalPct": 42.4
        },
        {
            "apiName": "DOS2_Quest4",
            "unlocked": true,
            "unlockedAt": "2018-11-23T20:36:59.000Z",
            "displayName": "The Great Escape",
            "description": "Flee Fort Joy for good",
            "iconUrl": "61b206a6d359175f0006dd1d9bdd926229fd0c30.jpg",
            "iconGrayUrl": "8b247d086a1c6158ecbebf00ae06a9860f7f57bd.jpg",
            "hidden": false,
            "globalPct": 54.4
        },
        {
            "apiName": "DOS2_Quest5",
            "unlocked": true,
            "unlockedAt": "2018-11-24T09:50:46.000Z",
            "displayName": "Walk at Liberty",
            "description": "Remove your Source Collar",
            "iconUrl": "c12b9c1e5e54fdddf63394785effda62cb6f1d48.jpg",
            "iconGrayUrl": "1ceb741104552119cae55dfb5951bfa1b21188ad.jpg",
            "hidden": false,
            "globalPct": 51.3
        },
        {
            "apiName": "DOS2_Quest6",
            "unlocked": false,
            "unlockedAt": null,
            "displayName": "Abound with Blessings",
            "description": "Face a higher power",
            "iconUrl": "383def303d33f5490dd6c3fd3872ffa79c34e170.jpg",
            "iconGrayUrl": "c705aa48da53e3c462419181e0da5feeedba01fe.jpg",
            "hidden": false,
            "globalPct": 47.3
        },
        {
            "apiName": "DOS2_Quest7",
            "unlocked": true,
            "unlockedAt": "2018-11-24T07:55:40.000Z",
            "displayName": "Spira, Spera",
            "description": "Arrive at the Sanctuary of Amadia",
            "iconUrl": "2a3c1688a41d0ec01612de83f81aad38555475e1.jpg",
            "iconGrayUrl": "373c832cb2b4ebed740c339a42cbcb5b78a44d21.jpg",
            "hidden": false,
            "globalPct": 49.3
        },
        {
            "apiName": "DOS2_Quest8",
            "unlocked": true,
            "unlockedAt": "2018-11-24T12:44:59.000Z",
            "displayName": "A Good and Faithful Servant",
            "description": "Rescue Gareth from Braccus' Armoury",
            "iconUrl": "ab33d6851524766eca280a0fc7daedd979641c93.jpg",
            "iconGrayUrl": "20d9bd5ef4a634e295e2558c87f4c7d8789d13c8.jpg",
            "hidden": false,
            "globalPct": 46.7
        },
        {
            "apiName": "DOS2_Quest9",
            "unlocked": true,
            "unlockedAt": "2018-11-25T09:09:07.000Z",
            "displayName": "His Father's Son",
            "description": "Defeat Alexandar in Fort Joy",
            "iconUrl": "9c07762f2b068f92f30b7743e792f07578ad898e.jpg",
            "iconGrayUrl": "8fd76fb93bf6eba0ba226c93655151b246e7ffd7.jpg",
            "hidden": false,
            "globalPct": 44
        },
        {
            "apiName": "DOS2_Quest10",
            "unlocked": false,
            "unlockedAt": null,
            "displayName": "Cat's Out of the Bag!",
            "description": "",
            "iconUrl": "b47b4f51ff9bd68758727bfc773b3f98b5de7083.jpg",
            "iconGrayUrl": "2023de61bdb4a7fd3625bb67db1c483dd1895a09.jpg",
            "hidden": true,
            "globalPct": 34
        },
        {
            "apiName": "DOS2_Quest11",
            "unlocked": false,
            "unlockedAt": null,
            "displayName": "Hammered",
            "description": "",
            "iconUrl": "a9cf7481e4d14adc513226c4aafd3a8be5f1c4c6.jpg",
            "iconGrayUrl": "241545de728bbc26222a1c9dc811520c1fd741c4.jpg",
            "hidden": true,
            "globalPct": 4.1
        },
        {
            "apiName": "DOS2_Quest12",
            "unlocked": false,
            "unlockedAt": null,
            "displayName": "Dragonslayer",
            "description": "",
            "iconUrl": "9b40e33d519ccd52abe0138f9b1cbac6a4b79fc7.jpg",
            "iconGrayUrl": "d0d5345de93b477edc6ecd1b4fd8c657165a7500.jpg",
            "hidden": true,
            "globalPct": 7.3
        },
        {
            "apiName": "DOS2_Quest13",
            "unlocked": false,
            "unlockedAt": null,
            "displayName": "The Weird Sister",
            "description": "",
            "iconUrl": "3abb63339a6d41a13ebec3fe5ec820d79adca30a.jpg",
            "iconGrayUrl": "11140f988def0c664b7e2cf19fb57820447c9266.jpg",
            "hidden": true,
            "globalPct": 43.3
        },
        {
            "apiName": "DOS2_Quest14",
            "unlocked": true,
            "unlockedAt": "2018-11-25T11:35:57.000Z",
            "displayName": "Sails That Glance in the Sun",
            "description": "Take command of the Lady Vengeance",
            "iconUrl": "46449b53a49b31b40b82ea4e7378e919e0dcb847.jpg",
            "iconGrayUrl": "4d2a77f83242b5f6df5223cda6b2afdd9f55db6e.jpg",
            "hidden": false,
            "globalPct": 42.2
        },
        {
            "apiName": "DOS2_Quest15",
            "unlocked": false,
            "unlockedAt": null,
            "displayName": "Scholar of Secret Arts",
            "description": "Welcome Tarquin to the Seekers' service",
            "iconUrl": "4a072e3a9e3ad826d28934be7c23f36cb2b884a6.jpg",
            "iconGrayUrl": "f0a4b79e287afa71def873cf446fd84b42ad503c.jpg",
            "hidden": false,
            "globalPct": 30.3
        },
        {
            "apiName": "DOS2_Quest16",
            "unlocked": false,
            "unlockedAt": null,
            "displayName": "Seascape",
            "description": "Escape Dallis' siege on the Lady Vengeance without killing every minion",
            "iconUrl": "093f485ee2f811a2413aee20b2cf10a4a4b1f5fc.jpg",
            "iconGrayUrl": "914bc63ed74caaf1e889dbd0b3bca585c69d01ca.jpg",
            "hidden": false,
            "globalPct": 38.5
        },
        {
            "apiName": "DOS2_Quest17",
            "unlocked": false,
            "unlockedAt": null,
            "displayName": "Heaven's Gate",
            "description": "Enter the Hall of Echoes",
            "iconUrl": "0fcb2839c83b1b975ac90c02d068a708bd3e8827.jpg",
            "iconGrayUrl": "2f64a20578086ffe4b1dab44ffabb7ed2d88a7bd.jpg",
            "hidden": false,
            "globalPct": 41.8
        },
        {
            "apiName": "DOS2_Quest18",
            "unlocked": false,
            "unlockedAt": null,
            "displayName": "Swashbuckler",
            "description": "",
            "iconUrl": "0e360b959647e65cce9dc1a8b33440515d4ae746.jpg",
            "iconGrayUrl": "0c50cafd4a199f3ddfd2a40dc317ec0357842cd2.jpg",
            "hidden": true,
            "globalPct": 6.5
        },
        {
            "apiName": "DOS2_Quest19",
            "unlocked": false,
            "unlockedAt": null,
            "displayName": "A Million of Waves",
            "description": "",
            "iconUrl": "d5af89a5ca1328096dcd1d741a8d50dbe5d0646a.jpg",
            "iconGrayUrl": "182da7dc4ccce35e1ee36c33184ea339b1ac8d7e.jpg",
            "hidden": true,
            "globalPct": 41.4
        },
        {
            "apiName": "DOS2_Quest20",
            "unlocked": false,
            "unlockedAt": null,
            "displayName": "The Meistr",
            "description": "Meet Meistr Siva",
            "iconUrl": "0f047d834cf7bcfb12e11537966d2f621da0b224.jpg",
            "iconGrayUrl": "08e578b10b793a8a3ce42f0bab7ff02fb44996a9.jpg",
            "hidden": false,
            "globalPct": 38.1
        },
        {
            "apiName": "DOS2_Quest21",
            "unlocked": false,
            "unlockedAt": null,
            "displayName": "Andabata",
            "description": "Become champion of the Driftwood Arena",
            "iconUrl": "4c58a0b0a424d39b048451e78923e2f05820da9a.jpg",
            "iconGrayUrl": "037a606c42b5695c250b1964d17b8b0e22e977e7.jpg",
            "hidden": false,
            "globalPct": 22.6
        },
        {
            "apiName": "DOS2_Quest22",
            "unlocked": true,
            "unlockedAt": "2018-11-25T06:00:19.000Z",
            "displayName": "Apprentice",
            "description": "Use your first Source Skill",
            "iconUrl": "cfbd9f28603da41587d659789c099a411ab72847.jpg",
            "iconGrayUrl": "a7095c89fde40ebfae1058ed6db1c33bca956b49.jpg",
            "hidden": false,
            "globalPct": 49.9
        },
        {
            "apiName": "DOS2_Quest23",
            "unlocked": false,
            "unlockedAt": null,
            "displayName": "Expert",
            "description": "Unlock your second Source Point slot",
            "iconUrl": "c753502ee8841b98524634e726ef109726d68c66.jpg",
            "iconGrayUrl": "6b676bb648304768cfa8a9b990b2a469c26c55c8.jpg",
            "hidden": false,
            "globalPct": 31.3
        },
        {
            "apiName": "DOS2_Quest24",
            "unlocked": false,
            "unlockedAt": null,
            "displayName": "Master",
            "description": "Unlock your third Source Point slot",
            "iconUrl": "06e8b856984e8e70a2bc9eed2142abd6d4cdb864.jpg",
            "iconGrayUrl": "f9baeb09a56cd2a0712f23b7e8a781d7f18945b4.jpg",
            "hidden": false,
            "globalPct": 27.5
        },
        {
            "apiName": "DOS2_Quest25",
            "unlocked": false,
            "unlockedAt": null,
            "displayName": "Furious Rebuke",
            "description": "",
            "iconUrl": "e667dcf08bb4ca9009c2601a0c5eb2b891a6adc4.jpg",
            "iconGrayUrl": "aced0c0e8459e5fb3c319b18077234bb82527823.jpg",
            "hidden": true,
            "globalPct": 5.6
        },
        {
            "apiName": "DOS2_Quest26",
            "unlocked": false,
            "unlockedAt": null,
            "displayName": "Iniquity Forgiven",
            "description": "",
            "iconUrl": "1dcda998164b42073ac9c845b901e2c5bfd79cf2.jpg",
            "iconGrayUrl": "75948e457c846a509873f8f68890ce0d210c2c26.jpg",
            "hidden": true,
            "globalPct": 18.1
        },
        {
            "apiName": "DOS2_Quest27",
            "unlocked": false,
            "unlockedAt": null,
            "displayName": "Isle of the Gods",
            "description": "",
            "iconUrl": "0ae21a1af05a353ed8b0e609b3282c17110ccc4f.jpg",
            "iconGrayUrl": "360a3a8723ccda8d3c73aad44997d3cd4042a394.jpg",
            "hidden": true,
            "globalPct": 23.7
        },
        {
            "apiName": "DOS2_Quest28",
            "unlocked": false,
            "unlockedAt": null,
            "displayName": "The Isle of Last Resort",
            "description": "",
            "iconUrl": "98728305fe30680b3a34a64e5f3086109858c85c.jpg",
            "iconGrayUrl": "45c5bc0741d36c647b648500a1482e9c4e230131.jpg",
            "hidden": true,
            "globalPct": 0.9
        },
        {
            "apiName": "DOS2_Quest29",
            "unlocked": false,
            "unlockedAt": null,
            "displayName": "Lawyer Up",
            "description": "",
            "iconUrl": "d45e4eb901aabd6ce6f12fd13512290f95b78e75.jpg",
            "iconGrayUrl": "14632a43ffd0b715d7e5d324d102ec24b5fc7d46.jpg",
            "hidden": true,
            "globalPct": 19
        },
        {
            "apiName": "DOS2_Quest30",
            "unlocked": false,
            "unlockedAt": null,
            "displayName": "What's in a Name?",
            "description": "",
            "iconUrl": "d1e44422a8ad50e3bfc868d21c8bfda4b9344d19.jpg",
            "iconGrayUrl": "64492de7ed9fb974aa5818ec640cc91f6a4471ba.jpg",
            "hidden": true,
            "globalPct": 17.9
        },
        {
            "apiName": "DOS2_Quest31",
            "unlocked": false,
            "unlockedAt": null,
            "displayName": "Existential Crisis",
            "description": "",
            "iconUrl": "b12bb49566f7456d296b3a58cefe1ed185bd4540.jpg",
            "iconGrayUrl": "6552498a8713f3694680a384d3ab0af4509ed206.jpg",
            "hidden": true,
            "globalPct": 16.7
        },
        {
            "apiName": "DOS2_Quest32",
            "unlocked": false,
            "unlockedAt": null,
            "displayName": "Infiltration",
            "description": "",
            "iconUrl": "a46fa9fc6498c778e9bdbd9139d0d76bebd7f03d.jpg",
            "iconGrayUrl": "cca07ecc3a1c255e83a3a5cf90d22f726ba02fac.jpg",
            "hidden": true,
            "globalPct": 8.6
        },
        {
            "apiName": "DOS2_Quest33",
            "unlocked": false,
            "unlockedAt": null,
            "displayName": "Anathema",
            "description": "",
            "iconUrl": "f96b7f4ce96cad65d6d99a73e3697e50e0212249.jpg",
            "iconGrayUrl": "4a3226a9bf22d3397cb9e9948617805200dc0ecc.jpg",
            "hidden": true,
            "globalPct": 8.1
        },
        {
            "apiName": "DOS2_Quest34",
            "unlocked": false,
            "unlockedAt": null,
            "displayName": "A Sheep in Wolf's Clothing",
            "description": "Escort Saheila outside without fighting the Lone Wolves",
            "iconUrl": "0427aef01aa040c0519c0e698bc83f6f8e7d6710.jpg",
            "iconGrayUrl": "73cede0b4c204ffe16fe158af76c3a4ce2fa0965.jpg",
            "hidden": false,
            "globalPct": 14.8
        },
        {
            "apiName": "DOS2_Quest35",
            "unlocked": false,
            "unlockedAt": null,
            "displayName": "Over to the Farther Coast",
            "description": "",
            "iconUrl": "3fea708900dad8160b0c6de2a7e0941fa5139a06.jpg",
            "iconGrayUrl": "32f5e2a45c917ab498836ce34d373320408f4329.jpg",
            "hidden": true,
            "globalPct": 10.5
        },
        {
            "apiName": "DOS2_Quest36",
            "unlocked": false,
            "unlockedAt": null,
            "displayName": "A Nest on High",
            "description": "",
            "iconUrl": "8c67ea761cac609bd43c5be99dcfb2cdeb9e59d4.jpg",
            "iconGrayUrl": "d34e527d357da4865008a7617b606ef1860a99aa.jpg",
            "hidden": true,
            "globalPct": 9.5
        },
        {
            "apiName": "DOS2_Quest37",
            "unlocked": false,
            "unlockedAt": null,
            "displayName": "Bridge Over Troubled Waters",
            "description": "Help free Mari from the Voidwoken",
            "iconUrl": "66d65af8020365fba87c01137d5c604b8e94f7b6.jpg",
            "iconGrayUrl": "9894609492fdfc116a291c4b985f1c640fa1f481.jpg",
            "hidden": false,
            "globalPct": 31.8
        },
        {
            "apiName": "DOS2_Quest38",
            "unlocked": false,
            "unlockedAt": null,
            "displayName": "Cur of Low Degree",
            "description": "",
            "iconUrl": "90ec7d3c233be52b51811e0c14a6d8fd2c56f15a.jpg",
            "iconGrayUrl": "ffd0f5a8a0600b5a0ef4d21b1f85d17f95a2a463.jpg",
            "hidden": true,
            "globalPct": 29.3
        },
        {
            "apiName": "DOS2_Quest39",
            "unlocked": false,
            "unlockedAt": null,
            "displayName": "The Good Doctor",
            "description": "",
            "iconUrl": "e8cc88cc0fd87b33aba59236960c5daf3cbf12f0.jpg",
            "iconGrayUrl": "b354e14c3b74fa87a22810582b626e17cf9fdebb.jpg",
            "hidden": true,
            "globalPct": 16.4
        },
        {
            "apiName": "DOS2_Quest40",
            "unlocked": false,
            "unlockedAt": null,
            "displayName": "Technical Eggstacy",
            "description": "",
            "iconUrl": "8916218814c32d1c5cf385e9573a5ab81d639384.jpg",
            "iconGrayUrl": "3174462cac281de4c4171f1655fca5cd7eb49588.jpg",
            "hidden": true,
            "globalPct": 1.4
        },
        {
            "apiName": "DOS2_Quest41",
            "unlocked": false,
            "unlockedAt": null,
            "displayName": "Death in the Pot",
            "description": "",
            "iconUrl": "d6725ff407e005b7e4fadfba8223a9347e7a1c0f.jpg",
            "iconGrayUrl": "a349c594be27faa51417d67c3a84623672d0756b.jpg",
            "hidden": true,
            "globalPct": 10.6
        },
        {
            "apiName": "DOS2_Quest42",
            "unlocked": false,
            "unlockedAt": null,
            "displayName": "Kiss of the Spider Woman",
            "description": "",
            "iconUrl": "7e6dff4dacc12bd686fe016e0c438f840fbfef15.jpg",
            "iconGrayUrl": "401bb4c8e9024d39ae940b3f32b18aff5a0ed04a.jpg",
            "hidden": true,
            "globalPct": 21
        },
        {
            "apiName": "DOS2_Quest43",
            "unlocked": false,
            "unlockedAt": null,
            "displayName": "Proud Parent",
            "description": "",
            "iconUrl": "2f1b559ff9f955c77820802001793b7062017ae0.jpg",
            "iconGrayUrl": "d911c7fc6c356ed8c49a323999883fd9cc8cedc6.jpg",
            "hidden": true,
            "globalPct": 25.2
        },
        {
            "apiName": "DOS2_Quest44",
            "unlocked": false,
            "unlockedAt": null,
            "displayName": "Island Hopper",
            "description": "Arrive at the Nameless Isle",
            "iconUrl": "fdc3d35c26649658f33752fee82ca18b08758a64.jpg",
            "iconGrayUrl": "bd18c7d2480cd2f358027e4ab01db9b3fa913bec.jpg",
            "hidden": false,
            "globalPct": 23.2
        },
        {
            "apiName": "DOS2_Quest45",
            "unlocked": false,
            "unlockedAt": null,
            "displayName": "Back to School",
            "description": "Enter the Academy",
            "iconUrl": "fa5439760c3d8a500ed77c01f1dee6afe4efdf1c.jpg",
            "iconGrayUrl": "b7295c1d57e6eca872c3122e388b04f1a9f2fd96.jpg",
            "hidden": false,
            "globalPct": 20.7
        },
        {
            "apiName": "DOS2_Quest46",
            "unlocked": false,
            "unlockedAt": null,
            "displayName": "Get In The Ring",
            "description": "Enter The Arena of the One",
            "iconUrl": "06cda90c971bdf729fe816b2d7ec4197c35d6220.jpg",
            "iconGrayUrl": "baebe15a2fa3eb149213672f35040031db169cbd.jpg",
            "hidden": false,
            "globalPct": 20.1
        },
        {
            "apiName": "DOS2_Quest48",
            "unlocked": false,
            "unlockedAt": null,
            "displayName": "The Seven Altars",
            "description": "Pray at every altar on the Nameless Isle",
            "iconUrl": "b8d97d719a7687824c513b60039daddf3129e611.jpg",
            "iconGrayUrl": "ab0257823ec441e49ded5e3480223066cde16f01.jpg",
            "hidden": false,
            "globalPct": 5.3
        },
        {
            "apiName": "DOS2_Quest49",
            "unlocked": false,
            "unlockedAt": null,
            "displayName": "Favoured Son",
            "description": "",
            "iconUrl": "cd6deefe2ddfb44a47a9652c27e86dda878513e3.jpg",
            "iconGrayUrl": "839daafb5e10bc517c5699fa1812df6870ed8ada.jpg",
            "hidden": true,
            "globalPct": 6
        },
        {
            "apiName": "DOS2_Quest50",
            "unlocked": false,
            "unlockedAt": null,
            "displayName": "Chosen",
            "description": "",
            "iconUrl": "28fe757b76d53c11206210f5e22827eb932c15cf.jpg",
            "iconGrayUrl": "efb7d1a000d3285e019db5cc4ef57902247b5ce8.jpg",
            "hidden": true,
            "globalPct": 13.8
        },
        {
            "apiName": "DOS2_Quest51",
            "unlocked": false,
            "unlockedAt": null,
            "displayName": "Serious Academic",
            "description": "",
            "iconUrl": "e7a7c757feb85c7024a8e2574206cddb7efa8f68.jpg",
            "iconGrayUrl": "ab1f90916f80a525374fdb73b8bb7601e4d39563.jpg",
            "hidden": true,
            "globalPct": 11.8
        },
        {
            "apiName": "DOS2_Quest54",
            "unlocked": false,
            "unlockedAt": null,
            "displayName": "The Promise",
            "description": "",
            "iconUrl": "b906dc99fad3d1f8d0df145f8780e3542e37ee6c.jpg",
            "iconGrayUrl": "c21846752ca257490f559c7b156e127e8589a882.jpg",
            "hidden": true,
            "globalPct": 2.6
        },
        {
            "apiName": "DOS2_Quest55",
            "unlocked": false,
            "unlockedAt": null,
            "displayName": "The Wreck of the Titan",
            "description": "Arrive at Arx",
            "iconUrl": "4f9ece252150e80a5b1413945f3602aa932cd440.jpg",
            "iconGrayUrl": "e467f82912fdb3000435769ac564fe0c3faca355.jpg",
            "hidden": false,
            "globalPct": 19.9
        },
        {
            "apiName": "DOS2_Quest56",
            "unlocked": false,
            "unlockedAt": null,
            "displayName": "The Back Door",
            "description": "",
            "iconUrl": "2ae08cb4b5f012f77c6dada69e66ab84734ce5d0.jpg",
            "iconGrayUrl": "c9c7f5722b873053c6252c702d64b0b0dff4dda8.jpg",
            "hidden": true,
            "globalPct": 14.7
        },
        {
            "apiName": "DOS2_Quest57",
            "unlocked": false,
            "unlockedAt": null,
            "displayName": "Puritan's Walk",
            "description": "",
            "iconUrl": "d90f882afeb79cb19417cdf4491aaacb641db13c.jpg",
            "iconGrayUrl": "14f7488632a5ee5a76ad807faefdc71c427bba11.jpg",
            "hidden": true,
            "globalPct": 1.9
        },
        {
            "apiName": "DOS2_Quest58",
            "unlocked": false,
            "unlockedAt": null,
            "displayName": "The Abysmal Sea",
            "description": "Defeated the Kraken",
            "iconUrl": "7c096eea47aed32635d7d449ad32c31a16909ea8.jpg",
            "iconGrayUrl": "aff2ea1435aaa30eb57881ddc4780adb9e683c60.jpg",
            "hidden": false,
            "globalPct": 13
        },
        {
            "apiName": "DOS2_Quest59",
            "unlocked": false,
            "unlockedAt": null,
            "displayName": "Risen",
            "description": "",
            "iconUrl": "6ef024b1057cd5d146240139becbbc6622f54e87.jpg",
            "iconGrayUrl": "fb8bf824579a9d0ebcb53612663053067cb05d59.jpg",
            "hidden": true,
            "globalPct": 10.8
        },
        {
            "apiName": "DOS2_Quest60",
            "unlocked": false,
            "unlockedAt": null,
            "displayName": "One For All",
            "description": "",
            "iconUrl": "b2896a8e911eafeea26e2daf49f7b705691bf514.jpg",
            "iconGrayUrl": "3b908677a7610d4eb611825073b07796b09f5db8.jpg",
            "hidden": true,
            "globalPct": 7.9
        },
        {
            "apiName": "DOS2_Quest61",
            "unlocked": false,
            "unlockedAt": null,
            "displayName": "Supreme Sacrifice",
            "description": "",
            "iconUrl": "2bd304acbd6d7ee93d5d41bfb19fabd1703a317d.jpg",
            "iconGrayUrl": "2dffb4d089cf2c283dfa65bbbefbf4e9fa60816b.jpg",
            "hidden": true,
            "globalPct": 6.1
        },
        {
            "apiName": "DOS2_Quest62",
            "unlocked": false,
            "unlockedAt": null,
            "displayName": "Return of the King",
            "description": "",
            "iconUrl": "6eddcb823984aa3972ac81b23446e216ed082c3d.jpg",
            "iconGrayUrl": "5ea5c242f02011ba30c6f098faa4889d02068202.jpg",
            "hidden": true,
            "globalPct": 4.4
        },
        {
            "apiName": "DOS2_Quest63",
            "unlocked": false,
            "unlockedAt": null,
            "displayName": "Angel and Demon",
            "description": "",
            "iconUrl": "656237e5a94195a4fe33777ff4edf340d363144d.jpg",
            "iconGrayUrl": "c08be8ef61ef3bf88f20a2280bdf715a7bcbf1c1.jpg",
            "hidden": true,
            "globalPct": 1.3
        },
        {
            "apiName": "DOS2_Quest64",
            "unlocked": false,
            "unlockedAt": null,
            "displayName": "A Dream Undone",
            "description": "",
            "iconUrl": "b88e5a4c3f8cf86b98e16c504de58ac8c50e2f98.jpg",
            "iconGrayUrl": "62a656cde170c43d696dbcb235757e13195b7144.jpg",
            "hidden": true,
            "globalPct": 1.2
        },
        {
            "apiName": "DOS2_Quest65",
            "unlocked": false,
            "unlockedAt": null,
            "displayName": "All-Father, Life-Shaper",
            "description": "",
            "iconUrl": "cb8fdf252b56e236821727c2edb3382bbec06756.jpg",
            "iconGrayUrl": "b41cc1a3796e108d1c1e67d75aab8e9eb55b2c30.jpg",
            "hidden": true,
            "globalPct": 7.3
        },
        {
            "apiName": "DOS2_Quest66",
            "unlocked": false,
            "unlockedAt": null,
            "displayName": "Demon's Embrace",
            "description": "",
            "iconUrl": "69c71b0866cd26138796dfe3c7d672bbaf676256.jpg",
            "iconGrayUrl": "469814fc1af8f22cea4778c48d49744e4a92f464.jpg",
            "hidden": true,
            "globalPct": 1.5
        },
        {
            "apiName": "DOS2_Quest67",
            "unlocked": false,
            "unlockedAt": null,
            "displayName": "An Apple a Day",
            "description": "",
            "iconUrl": "78078cfbc071ed274e21e359eb39154e7eb52750.jpg",
            "iconGrayUrl": "2027b098b5dc18ce3bbde4d1570c524a2c670846.jpg",
            "hidden": true,
            "globalPct": 7
        },
        {
            "apiName": "DOS2_Quest68",
            "unlocked": false,
            "unlockedAt": null,
            "displayName": "Stay Grounded",
            "description": "",
            "iconUrl": "c110c657b18513eb86770af0b73e0e61f904c389.jpg",
            "iconGrayUrl": "4a9f9e42aca277baf4b08cd52bffe8edca300ecc.jpg",
            "hidden": true,
            "globalPct": 4
        },
        {
            "apiName": "DOS2_Quest69",
            "unlocked": false,
            "unlockedAt": null,
            "displayName": "Liberator",
            "description": "",
            "iconUrl": "bf8d65aa1ebd5676dceddde4a49af19a3dd60871.jpg",
            "iconGrayUrl": "44c7a163ddd1c732b094dc22c4692d562676bc1f.jpg",
            "hidden": true,
            "globalPct": 5.9
        },
        {
            "apiName": "DOS2_Quest70",
            "unlocked": false,
            "unlockedAt": null,
            "displayName": "Eternal Salvation",
            "description": "",
            "iconUrl": "68a2ef88f146f7f7d5a06caedb0799b6af1c3124.jpg",
            "iconGrayUrl": "257beb39b693c47fb0f74f0c4b7463cbe60a313e.jpg",
            "hidden": true,
            "globalPct": 2
        },
        {
            "apiName": "DOS2_Quest71",
            "unlocked": false,
            "unlockedAt": null,
            "displayName": "The Adventure Begins...",
            "description": "",
            "iconUrl": "a21b33533a2b31f90eb5e075f3c440008513b1ef.jpg",
            "iconGrayUrl": "e6bf2922e8120406a587eb2a0037d462a5e59517.jpg",
            "hidden": true,
            "globalPct": 2.1
        },
        {
            "apiName": "DOS2_Quest72",
            "unlocked": false,
            "unlockedAt": null,
            "displayName": "A Wolf Avenged",
            "description": "",
            "iconUrl": "d35311a0e43db043d2fba7690516f0f5239c35de.jpg",
            "iconGrayUrl": "f6d82aaae5543f665e09f9f64af18df56d72ded0.jpg",
            "hidden": true,
            "globalPct": 5.4
        },
        {
            "apiName": "DOS2_Quest73",
            "unlocked": false,
            "unlockedAt": null,
            "displayName": "Fool Me Once",
            "description": "",
            "iconUrl": "32fa08d4bcd7e84c962c197414328ffb5bb1a1c6.jpg",
            "iconGrayUrl": "4d6f93b120479e60fff4710d6b313daef416b447.jpg",
            "hidden": true,
            "globalPct": 1.3
        },
        {
            "apiName": "DOS2_Quest74",
            "unlocked": false,
            "unlockedAt": null,
            "displayName": "Regicide",
            "description": "",
            "iconUrl": "172e3cf102944d50837ac6f4654f39b7aefeaac0.jpg",
            "iconGrayUrl": "ec485b36ff56b24601fa215b4c5af3b0d1ea9eb0.jpg",
            "hidden": true,
            "globalPct": 1.9
        },
        {
            "apiName": "DOS2_Quest76",
            "unlocked": false,
            "unlockedAt": null,
            "displayName": "Toy Story",
            "description": "",
            "iconUrl": "3c18a3df0a05453529ffd5427943f7955342065c.jpg",
            "iconGrayUrl": "d553f6d5435771fb5e87dfae23c0e12b7fd02d7b.jpg",
            "hidden": true,
            "globalPct": 10.7
        },
        {
            "apiName": "DOS2_Quest77",
            "unlocked": false,
            "unlockedAt": null,
            "displayName": "Lair of the White Worm",
            "description": "",
            "iconUrl": "27cc24faa183f7c279fd8048808d053fa62bdddb.jpg",
            "iconGrayUrl": "a8828f2d7516b1a46e208ea18f30ca15c612b833.jpg",
            "hidden": true,
            "globalPct": 15.8
        },
        {
            "apiName": "DOS2_Quest78",
            "unlocked": false,
            "unlockedAt": null,
            "displayName": "Cat Person",
            "description": "Rescue Arhu",
            "iconUrl": "86dfabbe0df7f6cc80abc76a47f9c091d0454eff.jpg",
            "iconGrayUrl": "2b342b9f7e82a9b90b0515bc25a0482386200087.jpg",
            "hidden": false,
            "globalPct": 11.4
        },
        {
            "apiName": "DOS2_Quest79",
            "unlocked": false,
            "unlockedAt": null,
            "displayName": "Doctor: Heal Thyself",
            "description": "",
            "iconUrl": "4878f46a89f35021318c51aed16540dc330fe7fd.jpg",
            "iconGrayUrl": "c478367fe1a23d4439bdb71d637aad5acc465d7e.jpg",
            "hidden": true,
            "globalPct": 13.8
        },
        {
            "apiName": "DOS2_Quest80",
            "unlocked": false,
            "unlockedAt": null,
            "displayName": "Deal with the Devil",
            "description": "",
            "iconUrl": "fbc52ecadb8550eaea29c1b7df24eb67565d1a2d.jpg",
            "iconGrayUrl": "7a2c8716449a946bbece9607df4ff7dcfbe1f3a4.jpg",
            "hidden": true,
            "globalPct": 2.8
        },
        {
            "apiName": "DOS2_Quest75",
            "unlocked": false,
            "unlockedAt": null,
            "displayName": "Royalty",
            "description": "",
            "iconUrl": "c94622a0c4b542286fe82dc70448eb952f5d936a.jpg",
            "iconGrayUrl": "de4d8ebd67a4c0e52ae0cbdc626c1f9c54406b39.jpg",
            "hidden": true,
            "globalPct": 2.5
        },
        {
            "apiName": "DOS2_Quest81",
            "unlocked": false,
            "unlockedAt": null,
            "displayName": "Masquerade",
            "description": "",
            "iconUrl": "bf9a81271c5dfee1e7fa5a8f312b63e146f11cc2.jpg",
            "iconGrayUrl": "3a4bcb1c2ba293b2dd4b7f9159b26784f3e2afe5.jpg",
            "hidden": true,
            "globalPct": 23.5
        },
        {
            "apiName": "DOS2_Quest82",
            "unlocked": false,
            "unlockedAt": null,
            "displayName": "Sourcerer",
            "description": "Complete the game in Explorer Mode",
            "iconUrl": "8a3ca92dde3f7f2903e49cdbd7f349989b5d63bd.jpg",
            "iconGrayUrl": "8f6675a57de417f2dd9778aeff3586c5ed85706f.jpg",
            "hidden": false,
            "globalPct": 11.7
        },
        {
            "apiName": "DOS2_Quest83",
            "unlocked": false,
            "unlockedAt": null,
            "displayName": "Godwoken",
            "description": "Complete the game in Classic Mode",
            "iconUrl": "3fbc6f6741257f93b0c3125b19e415cfd3cd7941.jpg",
            "iconGrayUrl": "588a8d182872e4d1f09e4c2381c725b8d1c6d7c2.jpg",
            "hidden": false,
            "globalPct": 10
        },
        {
            "apiName": "DOS2_Quest84",
            "unlocked": false,
            "unlockedAt": null,
            "displayName": "Divine",
            "description": "Complete the game in Tactician Mode",
            "iconUrl": "adb5f13bca30f50480a790e46f65c8af9203d76e.jpg",
            "iconGrayUrl": "d2aa6c80333592fec73c2b123718dcf3620d2e56.jpg",
            "hidden": false,
            "globalPct": 3.3
        },
        {
            "apiName": "DOS2_Quest85",
            "unlocked": false,
            "unlockedAt": null,
            "displayName": "Arcane Author",
            "description": "Craft a scroll",
            "iconUrl": "553a70fc29d974aafa8eb8b32a6b14ee21ae93c7.jpg",
            "iconGrayUrl": "ac268765ca48d4656e52e510af09eca78e8656b5.jpg",
            "hidden": false,
            "globalPct": 24
        },
        {
            "apiName": "DOS2_Quest86",
            "unlocked": false,
            "unlockedAt": null,
            "displayName": "Took a Great Fall",
            "description": "",
            "iconUrl": "9857c395806704c51a75b562ca6b935f83ab5718.jpg",
            "iconGrayUrl": "73b47466c2ff122b76e7f47e413232290993d453.jpg",
            "hidden": true,
            "globalPct": 35.4
        },
        {
            "apiName": "DOS2_Quest87",
            "unlocked": true,
            "unlockedAt": "2018-11-25T11:21:02.000Z",
            "displayName": "Skillcrafter",
            "description": "Craft a skill",
            "iconUrl": "e4fc015aa04969bb84a27016cd6b4d2d7f337e4a.jpg",
            "iconGrayUrl": "7594fede54ac297930a18cc41c9e36a7b7ad99f0.jpg",
            "hidden": false,
            "globalPct": 24.3
        },
        {
            "apiName": "DOS2_Quest88",
            "unlocked": false,
            "unlockedAt": null,
            "displayName": "Runemaster",
            "description": "Equip runes to all of an item's available slots",
            "iconUrl": "13ab5363a310a64a89b76f4d9d69bd94a5493b42.jpg",
            "iconGrayUrl": "91f95455b0afb3582d36db79c6d18ef7bf65b6ef.jpg",
            "hidden": false,
            "globalPct": 37
        },
        {
            "apiName": "DOS2_Quest89",
            "unlocked": false,
            "unlockedAt": null,
            "displayName": "Spirit Animal",
            "description": "Speak to an animal's spirit",
            "iconUrl": "c013ef22ece989fe35167c14faaff8fd8201af62.jpg",
            "iconGrayUrl": "e1d94d602d0680ffd72f4d3b38e517d05ad96dcb.jpg",
            "hidden": false,
            "globalPct": 30.9
        },
        {
            "apiName": "DOS2_Quest90",
            "unlocked": false,
            "unlockedAt": null,
            "displayName": "Curse Thine Enemies",
            "description": "Use the Curse skill",
            "iconUrl": "e8142cb260179545c6a138109e00887b9960aa3c.jpg",
            "iconGrayUrl": "302b21b7e2267bf1ddd73167199d67a97b30cba1.jpg",
            "hidden": false,
            "globalPct": 2.9
        },
        {
            "apiName": "DOS2_Quest91",
            "unlocked": true,
            "unlockedAt": "2018-11-20T14:47:52.000Z",
            "displayName": "Hero",
            "description": "",
            "iconUrl": "3ea69158e50ac2b2611f48b1e52a58620294ec7b.jpg",
            "iconGrayUrl": "5ac9abd911b2abeeaa95153e9598e8aca2da5263.jpg",
            "hidden": true,
            "globalPct": 44.4
        },
        {
            "apiName": "DOS2_Quest92",
            "unlocked": false,
            "unlockedAt": null,
            "displayName": "Villain",
            "description": "",
            "iconUrl": "fb3f1fad894c291b69f19191f6c41fbc43fd5588.jpg",
            "iconGrayUrl": "9c28976f09658a1228c82360d4505ffeed9848cb.jpg",
            "hidden": true,
            "globalPct": 10.5
        },
        {
            "apiName": "DOS2_Quest93",
            "unlocked": false,
            "unlockedAt": null,
            "displayName": "Convincing",
            "description": "Win a persuasion event",
            "iconUrl": "488b436fec983eded73cb43b6c09469a38e1e324.jpg",
            "iconGrayUrl": "3fdef23546ea1f918ee73aa715e2f792c9eb28b5.jpg",
            "hidden": false,
            "globalPct": 67.6
        },
        {
            "apiName": "DOS2_Quest94",
            "unlocked": true,
            "unlockedAt": "2018-11-20T07:52:39.000Z",
            "displayName": "Thief",
            "description": "Perform a successful theft",
            "iconUrl": "ac418243203c3caea7b736bdaae73621b0c75743.jpg",
            "iconGrayUrl": "6e98c8a613d2d28a22131238a4048a1bc97b8dc2.jpg",
            "hidden": false,
            "globalPct": 73
        },
        {
            "apiName": "DOS2_Quest95",
            "unlocked": true,
            "unlockedAt": "2018-11-20T14:45:34.000Z",
            "displayName": "Grenadier",
            "description": "Craft a grenade",
            "iconUrl": "073f48dfde44feb532c30aa93daaee37f9979395.jpg",
            "iconGrayUrl": "d5821f0ecea43b80917fb3d7625593fa3331382d.jpg",
            "hidden": false,
            "globalPct": 13.9
        },
        {
            "apiName": "DOS2_Quest96",
            "unlocked": false,
            "unlockedAt": null,
            "displayName": "Criminal Intent",
            "description": "Get caught breaking the law",
            "iconUrl": "5bf0692cb6162cd0e20b96c8e85bac217464a986.jpg",
            "iconGrayUrl": "3a58182f28e0d128c7faa6c406087195c8a46365.jpg",
            "hidden": false,
            "globalPct": 30.2
        },
        {
            "apiName": "DOS2_Quest97",
            "unlocked": false,
            "unlockedAt": null,
            "displayName": "Venture Forth",
            "description": "Successfully begin a match in Arena Mode",
            "iconUrl": "c87afa6eff91bf1e4196a892b1e3c777790875d1.jpg",
            "iconGrayUrl": "1f29576df2cbb20366bd7d2640c3dd28d894d22f.jpg",
            "hidden": false,
            "globalPct": 5.8
        },
        {
            "apiName": "DOS2_Quest98",
            "unlocked": false,
            "unlockedAt": null,
            "displayName": "Gather Your Party",
            "description": "Successfully begin a Game Master session",
            "iconUrl": "791f63fd07a3a9bd05a2d2e4299605b3850594b4.jpg",
            "iconGrayUrl": "2b8c43b181cda65114dc7d500944dcad0ae33fc5.jpg",
            "hidden": false,
            "globalPct": 4.4
        },
        {
            "apiName": "DOS2_Quest99",
            "unlocked": false,
            "unlockedAt": null,
            "displayName": "For Honour",
            "description": "Complete the game in Honour Mode",
            "iconUrl": "cb815d2bdcc49bc73ae0b1382528aeadd27011db.jpg",
            "iconGrayUrl": "00676040f97de8f215f139984de69e742781e934.jpg",
            "hidden": false,
            "globalPct": 1
        },
        {
            "apiName": "DOS2_Quest100",
            "unlocked": false,
            "unlockedAt": null,
            "displayName": "A Song Unsung",
            "description": "",
            "iconUrl": "3e6a5354398c561cfcdfc9bc9d34b0ab54fa6c44.jpg",
            "iconGrayUrl": "5d9a8939dc7fc089592d7a317c2cb8067c36c7c5.jpg",
            "hidden": true,
            "globalPct": 9.6
        }
    ],
    "playtimeForever": 1827,
    "lastPlayedTs": "2018-11-25T11:57:56.000Z",
    "iconUrl": "https://media.steampowered.com/steamcommunity/public/images/apps/435150/519a99caef7c5e2b4625c8c2fa0620fb66a752f3.jpg",
    "lastUnlockedAt": "2018-11-25T11:35:57.000Z",
    "lastUnlockName": "Sails That Glance in the Sun",
    "preview": [
        {
            "apiName": "DOS2_Quest14",
            "displayName": "Sails That Glance in the Sun",
            "unlocked": true,
            "unlockedAt": "2018-11-25T11:35:57.000Z",
            "iconUrl": "46449b53a49b31b40b82ea4e7378e919e0dcb847.jpg",
            "iconGrayUrl": "4d2a77f83242b5f6df5223cda6b2afdd9f55db6e.jpg",
            "globalPct": 42.2
        },
        {
            "apiName": "DOS2_Quest87",
            "displayName": "Skillcrafter",
            "unlocked": true,
            "unlockedAt": "2018-11-25T11:21:02.000Z",
            "iconUrl": "e4fc015aa04969bb84a27016cd6b4d2d7f337e4a.jpg",
            "iconGrayUrl": "7594fede54ac297930a18cc41c9e36a7b7ad99f0.jpg",
            "globalPct": 24.3
        },
        {
            "apiName": "DOS2_Quest9",
            "displayName": "His Father's Son",
            "unlocked": true,
            "unlockedAt": "2018-11-25T09:09:07.000Z",
            "iconUrl": "9c07762f2b068f92f30b7743e792f07578ad898e.jpg",
            "iconGrayUrl": "8fd76fb93bf6eba0ba226c93655151b246e7ffd7.jpg",
            "globalPct": 44
        },
        {
            "apiName": "DOS2_Quest22",
            "displayName": "Apprentice",
            "unlocked": true,
            "unlockedAt": "2018-11-25T06:00:19.000Z",
            "iconUrl": "cfbd9f28603da41587d659789c099a411ab72847.jpg",
            "iconGrayUrl": "a7095c89fde40ebfae1058ed6db1c33bca956b49.jpg",
            "globalPct": 49.9
        },
        {
            "apiName": "DOS2_Quest8",
            "displayName": "A Good and Faithful Servant",
            "unlocked": true,
            "unlockedAt": "2018-11-24T12:44:59.000Z",
            "iconUrl": "ab33d6851524766eca280a0fc7daedd979641c93.jpg",
            "iconGrayUrl": "20d9bd5ef4a634e295e2558c87f4c7d8789d13c8.jpg",
            "globalPct": 46.7
        },
        {
            "apiName": "DOS2_Quest5",
            "displayName": "Walk at Liberty",
            "unlocked": true,
            "unlockedAt": "2018-11-24T09:50:46.000Z",
            "iconUrl": "c12b9c1e5e54fdddf63394785effda62cb6f1d48.jpg",
            "iconGrayUrl": "1ceb741104552119cae55dfb5951bfa1b21188ad.jpg",
            "globalPct": 51.3
        }
    ]
}